examples/test.py
polars_api/__init__.py
polars_api/api.py
tests/test_api.py
polars_api-0.1.5.dist-info/LICENSE
polars_api-0.1.5.dist-info/METADATA
polars_api-0.1.5.dist-info/WHEEL
polars_api-0.1.5.dist-info/top_level.txt
polars_api-0.1.5.dist-info/RECORD
