Metadata-Version: 2.2
Name: polars-api
Version: 0.1.5
Summary: Polars extension for dealing with REST APIs
Author-email: Diego Garcia Lozano <diegoglozano96@gmail.com>
Project-URL: Homepage, https://diegoglozano.github.io/polars-api/
Project-URL: Repository, https://github.com/diegoglozano/polars-api
Project-URL: Documentation, https://diegoglozano.github.io/polars-api/
Keywords: python
Classifier: Intended Audience :: Developers
Classifier: Programming Language :: Python
Classifier: Programming Language :: Python :: 3
Classifier: Programming Language :: Python :: 3.9
Classifier: Programming Language :: Python :: 3.10
Classifier: Programming Language :: Python :: 3.11
Classifier: Programming Language :: Python :: 3.12
Classifier: Programming Language :: Python :: 3.13
Classifier: Topic :: Software Development :: Libraries :: Python Modules
Requires-Python: <4.0,>=3.9
License-File: LICENSE
Requires-Dist: httpx>=0.28.1
Requires-Dist: polars>=1.19.0
